hundredandten/__init__.py
hundredandten/actions.py
hundredandten/constants.py
hundredandten/decisions.py
hundredandten/deck.py
hundredandten/events.py
hundredandten/game.py
hundredandten/group.py
hundredandten/hundred_and_ten_error.py
hundredandten/round.py
hundredandten/trick.py
hundredandten-1.11.54.dist-info/licenses/LICENSE
hundredandten-1.11.54.dist-info/METADATA
hundredandten-1.11.54.dist-info/WHEEL
hundredandten-1.11.54.dist-info/top_level.txt
hundredandten-1.11.54.dist-info/RECORD
