Metadata-Version: 2.4
Name: hundredandten
Version: 1.11.54
Summary: A package to play the game Hundred and Ten
Author: Seamus Lowry
Classifier: License :: OSI Approved :: MIT License
Classifier: Operating System :: OS Independent
Classifier: Programming Language :: Python :: 3
Requires-Python: >=3.11
License-File: LICENSE
Provides-Extra: lint
Requires-Dist: pylint==4.0.4; extra == "lint"
Requires-Dist: pyright==1.1.408; extra == "lint"
Provides-Extra: publish
Requires-Dist: build==1.4.0; extra == "publish"
Requires-Dist: twine==6.2.0; extra == "publish"
Provides-Extra: test
Requires-Dist: coverage==7.13.2; extra == "test"
Requires-Dist: pytest==9.0.2; extra == "test"
Dynamic: license-file
